setup.py
usa_today/__init__.py
usa_today/usa_today.py
usa_today/usa_today_api_key.py
usa_today.egg-info/PKG-INFO
usa_today.egg-info/SOURCES.txt
usa_today.egg-info/dependency_links.txt
usa_today.egg-info/top_level.txt