Metadata-Version: 1.0
Name: usa-today
Version: 1.0
Summary: Python wrapper for the USA Today Census API.
Home-page: https://github.com/codeforamerica/USA-Today-Census-Python
Author: Zach Williams
Author-email: zach@codeforamerica.org
License: BSD
Keywords: usa_today,USA Today,census,usa today census,census api
Platform: UNKNOWN
Classifier: Development Status :: 5 - Production/Stable
Classifier: Intended Audience :: Developers
Classifier: Natural Language :: English
Classifier: Operating System :: OS Independent
Classifier: Programming Language :: Python :: 2
Classifier: Topic :: Internet
Classifier: Topic :: Internet :: WWW/HTTP
